[
  {
    "id": "1774356904808",
    "title": "싱가포르 디즈니 크루즈 6일",
    "cruiseline": "디즈니 크루즈",
    "ship": "디즈니 어드벤쳐호",
    "category": "아시아중동",
    "nights": 4,
    "desc": "20만톤급 디즈니 어드벤쳐호 탑승, 싱가포르 필수관광 포함 디즈니 크루즈 4박6일 여행",
    "images": [
      "https://www.cruznara.com/upload/cruznara/image/goods/main/30000086/cruznara_cm9900_30000404.png",
      "https://www.cruznara.com/upload/cruznara/image/goods/main/30000086/cruznara_cm9900_30000402.png",
      "https://www.cruznara.com/upload/cruznara/image/goods/main/30000086/cruznara_cm9900_30000403.png",
      "https://www.cruznara.com/upload/cruznara/image/goods/main/30000086/cruznara_cm9900_30000401.png",
      "https://www.cruznara.com/upload/cruznara/image/goods/main/30000086/cruznara_cm9900_30000405.png"
    ],
    "introImages": [
      "https://www.cruznara.com/upload/cruznara/ckeditor/202603/cruznara_596eb19d7f5746d5a2460f77f668f1cb.jpg",
      "https://www.cruznara.com/upload/cruznara/ckeditor/202603/cruznara_82b688f837fd4e4a9ff50fda8b2dfc96.jpg",
      "https://www.cruznara.com/upload/cruznara/ckeditor/202603/cruznara_7a92496a2185434eba9b8b898308f17b.jpg",
      "https://www.cruznara.com/upload/cruznara/ckeditor/202603/cruznara_3f7b5259eecd46f48a8dd5c14cd8ba91.png",
      "https://www.cruznara.com/upload/cruznara/ckeditor/202603/cruznara_37a878bf546445f2ab69966e18aefaaa.jpg",
      "https://www.cruznara.com/upload/cruznara/ckeditor/202603/cruznara_1feae9fd65544321aca9a6a3f408e2a9.jpg",
      "https://www.cruznara.com/upload/cruznara/ckeditor/202603/cruznara_e0aa9fa7c92641788b80298dd065c766.png",
      "https://www.cruznara.com/upload/cruznara/ckeditor/202603/cruznara_7dca6fbacfac498f934752fe19efe19e.jpg"
    ],
    "departures": [
      "2026.06.21",
      "2026.06.21"
    ],
    "fares": [
      {
        "type": "내측",
        "price": 3090000,
        "note": "원화 기준"
      }
    ],
    "itinerary": [
      {
        "day": "1",
        "date": "20260621",
        "city": "인천",
        "description": "[12:30] 인천국제공항 2터미널 3층 미팅\n\n[16:10] 인천국제공항 출발 (OZ751편 6시간 20분 직항)\n\n[21:30] 싱가포르국제공항 도착\n\n호텔 투숙 및 휴식",
        "images": []
      },
      {
        "day": "2",
        "date": "20260622",
        "city": "싱가포르",
        "description": "호텔 조식 후 가이드 미팅\n\n가이드 미팅 후 싱가포르 시내 이동 및 관광\n\n싱가포르 관광\n\n- 보타닉가든\n\n- 멀라이언파크\n\n- 에스플러네이드(외관)\n\n크루즈 터미널 도착, 크루즈 승선 수속\n\nSHIP TOUR(선내 주요시설, 위치 안내)\n\n[16:00] 싱가포르 출항",
        "images": [
          "https://www.cruznara.com/upload/cruznara/image/tourinfo/SG/SIN/cruznara_ti0120_30000087.jpg",
          "https://www.cruznara.com/upload/cruznara/image/tourinfo/SG/SIN/cruznara_ti0120_30000573.png",
          "https://www.cruznara.com/upload/cruznara/image/tourinfo/SG/SIN/cruznara_ti0120_30000574.png",
          "https://www.cruznara.com/upload/cruznara/image/tourinfo/SG/SIN/cruznara_ti0120_30000575.png",
          "https://www.cruznara.com/upload/cruznara/image/tourinfo/SG/SIN/cruznara_ti0120_30000136.jpg"
        ]
      },
      {
        "day": "3",
        "date": "20260623",
        "city": "전일해상",
        "description": "전일해상_디즈니 어드벤처❉Adventure of Disney❉\n\n전일해상일에 바다 위에서 펼쳐지는 디즈니의 마법\n\n디즈니 어드벤처호에서는 하루 종일 즐길 거리가 가득합니다. 해상에서 가장 긴 롤러코스터 &lsquo;Ironcycle Test Run&rsquo;부터 디즈니 캐릭터와 함께하는 인터랙티브 쇼, 그리고 밤에는 브로드웨이 스타일의 공연이 대극장에서 펼 쳐집니다. 토이 스토리와 산 프란소쿄, 이매지네이션 가든 등 테마 공간도 풍성해 아이와 어른 모두에게 마법 같 은 하루를 선사합니다.",
        "images": []
      },
      {
        "day": "4",
        "date": "20260624",
        "city": "전일해상",
        "description": "전일해상_디즈니 어드벤처\n\n❉Adventure of Disney❉\n\n전일해상일에 바다 위에서 펼쳐지는 디즈니의 마법\n\n디즈니 어드벤처호에서는 하루 종일 즐길 거리가 가득합니다. 해상에서 가장 긴 롤러코스터 &lsquo;Ironcycle Test Run&rsquo;부터 디즈니 캐릭터와 함께하는 인터랙티브 쇼, 그리고 밤에는 브로드웨이 스타일의 공연이 대극장에서 펼 쳐집니다. 토이 스토리와 산 프란소쿄, 이매지네이션 가든 등 테마 공간도 풍성해 아이와 어른 모두에게 마법 같 은 하루를 선사합니다.",
        "images": []
      },
      {
        "day": "5",
        "date": "20260625",
        "city": "싱가포르",
        "description": "[07:00] 싱가포르 입항\n\n선내 조식 후 크루즈 체크아웃 및 가이드 미팅\n\n싱가포르 관광\n\n- 가든스 바이 더 베이\n\n- 센토사 케이블카, 실로소비치\n\n- 슈퍼트리쇼\n\n- 클락키 자유시간\n\n관광 후 공항으로 이동\n\n[22:50] 싱가포르국제공항 출발",
        "images": [
          "https://www.cruznara.com/upload/cruznara/image/tourinfo/SG/SIN/cruznara_ti0120_30000151.jpg",
          "https://www.cruznara.com/upload/cruznara/image/tourinfo/SG/SIN/cruznara_ti0120_30000152.jpg",
          "https://www.cruznara.com/upload/cruznara/image/tourinfo/SG/SIN/cruznara_ti0120_30000153.jpg"
        ]
      },
      {
        "day": "6",
        "date": "20260626",
        "city": "인천",
        "description": "[06:40] 인천국제공항 2터미널 도착\n\n[OZ752] 싱가포르 -> 인천 소요시간: 06시간 50분",
        "images": []
      }
    ],
    "flightOut": {
      "airline": "아시아나항공",
      "flightNo": "OZ751",
      "depTime": "16:10",
      "arrTime": "21:30",
      "depDate": "2026.06.21",
      "arrDate": "2026.06.21",
      "depPort": "인천ICN",
      "arrPort": "싱가폴SIN"
    },
    "flightIn": {
      "airline": "아시아나항공",
      "flightNo": "OZ752",
      "depTime": "22:50",
      "arrTime": "06:40",
      "depDate": "2026.06.26",
      "arrDate": "2026.06.26",
      "depPort": "싱가폴SIN",
      "arrPort": "인천ICN"
    },
    "included": [
      "왕복 항공권 - 기본 이코노미석",
      "크루즈 선실 - 크루즈 내측 2인 1실",
      "호텔 (일정표 상의 명시된 호텔 혹은 동급)",
      "일정표상의 명시된 식사 포함",
      "여행자 보험 - DB손해보험 또는 현대해상 해외여행자 손해보험 최대1억원",
      "기항지에 따라 전용 버스 이용",
      "출발부터 도착까지 전문 베테랑 인솔자 동행",
      "일정표상에 명시된 승/하선지 투어 일체 포함"
    ],
    "excluded": [
      "항공좌석 변경 - 좌석 업그레이드 요청 시 추가비용 발생",
      "크루즈 선실 - 싱글 객실 또는 객실 타입 변경 요청 시 추가비용 발생",
      "항만세 - 390,000원(1인당)",
      "크루즈 선내 팁 - 국제적 관례에 따른 선내 팁 : 크루즈 1인 1박당 $16",
      "크루즈내 유료 시설 이용 및 기타 개인 경비",
      "환율변동 추가금"
    ],
    "updatedAt": "2026-03-24T12:55:04.808Z"
  }
]